circleparse/__init__.py
circleparse/beatmap.py
circleparse/constants.py
circleparse/curves.py
circleparse/enums.py
circleparse/hitobject.py
circleparse/mathhelper.py
circleparse/replay.py
osrparse/__init__.py
osrparse/enums.py
osrparse/replay.py
tests/__init__.py
tests/replay_test.py
circleparse-6.4.1.dist-info/LICENSE
circleparse-6.4.1.dist-info/METADATA
circleparse-6.4.1.dist-info/WHEEL
circleparse-6.4.1.dist-info/top_level.txt
circleparse-6.4.1.dist-info/RECORD
