Metadata-Version: 2.1
Name: circleparse
Version: 6.4.1
Summary: Parser for osr files and lzma replay streams for osu!
Home-page: https://github.com/circleguard/circleparse
Author: Liam DeVoe
Author-email: orionldevoe@gmail.com
License: MIT
Download-URL: https://github.com/circleguard/circleparse/tarball/v6.4.1
Keywords: osu!, osr, replay, replays, parsing, parser, python
Platform: UNKNOWN
Classifier: Topic :: Games/Entertainment
Classifier: Topic :: Software Development :: Libraries
Classifier: Intended Audience :: Developers
Classifier: Operating System :: OS Independent
Classifier: Programming Language :: Python :: 3
